tests/__init__.py
tests/test_dataset.py
tests/test_field.py
tests/test_loader.py
tests/test_model.py
tests/test_operator.py
torchtable/__init__.py
torchtable/__version__.py
torchtable/custom_types.py
torchtable/utils.py
torchtable/dataset/__init__.py
torchtable/dataset/core.py
torchtable/field/__init__.py
torchtable/field/core.py
torchtable/field/datetime.py
torchtable/loader/__init__.py
torchtable/loader/core.py
torchtable/model/__init__.py
torchtable/model/core.py
torchtable/operator/__init__.py
torchtable/operator/core.py
torchtable-0.1.0.dist-info/LICENSE
torchtable-0.1.0.dist-info/METADATA
torchtable-0.1.0.dist-info/WHEEL
torchtable-0.1.0.dist-info/top_level.txt
torchtable-0.1.0.dist-info/RECORD
