Metadata-Version: 2.1
Name: torchtable
Version: 0.1.0
Summary: Tools for processing tabular datasets for PyTorch
Home-page: https://github.com/keitakurita/torchtable
Author: Keita Kurita
Author-email: keita.kurita@gmail.com
License: MIT
Keywords: PyTorch,deep learning,machine learning
Platform: UNKNOWN
Requires-Python: >=3.6
Requires-Dist: numpy
Requires-Dist: pandas
Requires-Dist: scipy
Requires-Dist: torch (>=1.0.0)
